README.md
setup.py
relocate/__init__.py
relocate/relocate.py
relocate.egg-info/PKG-INFO
relocate.egg-info/SOURCES.txt
relocate.egg-info/dependency_links.txt
relocate.egg-info/not-zip-safe
relocate.egg-info/top_level.txt