Metadata-Version: 2.1
Name: relocate
Version: 2.0.0
Summary: Relocate is a Python Package by Sandip Palit. It will help you in organising your files into distinct folders.
Home-page: UNKNOWN
Author: Sandip Palit
Author-email: sandippalit009@gmail.com
License: MIT
Platform: UNKNOWN
Requires-Python: >=3.6
